pycloudstack/__init__.py
pycloudstack/artifacts.py
pycloudstack/cluster.py
pycloudstack/cmdrunner.py
pycloudstack/dut.py
pycloudstack/msr.py
pycloudstack/registry.py
pycloudstack/virtxml.py
pycloudstack/vmguest.py
pycloudstack/vmimg.py
pycloudstack/vmm.py
pycloudstack/vmparam.py
pycloudstack/templates/legacy-base.xml
pycloudstack/templates/ovmf-base.xml
pycloudstack/templates/sgx-base.xml
pycloudstack/templates/tdx-base.xml
pycloustack-0.0.7.dist-info/LICENSE
pycloustack-0.0.7.dist-info/METADATA
pycloustack-0.0.7.dist-info/WHEEL
pycloustack-0.0.7.dist-info/top_level.txt
pycloustack-0.0.7.dist-info/RECORD
