Metadata-Version: 2.1
Name: pycloustack
Version: 0.0.7
Summary: Python package to manage hypervisor/docker/kubernetes stacks
Author-email: Lu Ken <ken.lu@intel.com>, "Hao, Ruomeng" <ruomeng.hao@intel.com>
License: Apache License
Project-URL: Homepage, https://github.com/intel/tdx-tools
Project-URL: Bug Tracker, https://github.com/intel/tdx-tools/issues
Classifier: Programming Language :: Python :: 3
Classifier: License :: OSI Approved :: Apache Software License
Classifier: Operating System :: POSIX :: Linux
Classifier: Topic :: Software Development :: Testing
Requires-Python: >=3.6
License-File: LICENSE
Requires-Dist: requests (>2.22.0)
Requires-Dist: py-cpuinfo (>=7.0.0)
Requires-Dist: pyyaml (>=5.4.1)
Requires-Dist: libvirt-python
Requires-Dist: wheel
Requires-Dist: docker
Requires-Dist: py-libnuma
